README.md
setup.py
dns_dnspod.egg-info/PKG-INFO
dns_dnspod.egg-info/SOURCES.txt
dns_dnspod.egg-info/dependency_links.txt
dns_dnspod.egg-info/top_level.txt
pydnspod/__init__.py
pydnspod/base.py
pydnspod/domain.py
pydnspod/record.py
pydnspod/user.py