Metadata-Version: 2.1
Name: dns-dnspod
Version: 1.0.0
Summary: manage dnspod domain and records
Home-page: https://github.com/x-hezhang/pydnspod
Author: zhanghe
Author-email: x_hezhang@126.com
License: GPLv3
Keywords: dns,dnspod
Platform: UNKNOWN
